{
"Formularios": [
	{
		"id" : 1,
		"fecha_inicio" : "2020-01-01T10:00:00Z",
		"fecha_fin" : "2022-07-12T10:00:00Z",
		"nombreCampaña" : null,
		"objetivo" : null,
		"descripcion" : null,
		"lider" : null,
		"emailLider" : null,
		"telefonoLider" : null,
		"id_plantilla" : 1,
		"id_usuario" : "8a4b6394-0a7d-4ec6-90a8-393dbccb0548"
	},
	{
		"id" : 2,
		"fecha_inicio" : "2020-01-01T10:00:00Z",
		"fecha_fin" : "2022-07-12T10:00:00Z",
		"nombreCampaña" : null,
		"objetivo" : null,
		"descripcion" : null,
		"lider" : null,
		"emailLider" : null,
		"telefonoLider" : null,
		"id_plantilla" : 2,
		"id_usuario" : "8a4b6394-0a7d-4ec6-90a8-393dbccb0548"
	},
	{
		"id" : 3,
		"fecha_inicio" : "2020-01-01T10:00:00Z",
		"fecha_fin" : "2022-07-12T10:00:00Z",
		"nombreCampaña" : null,
		"objetivo" : null,
		"descripcion" : null,
		"lider" : null,
		"emailLider" : null,
		"telefonoLider" : null,
		"id_plantilla" : 3,
		"id_usuario" : "8a4b6394-0a7d-4ec6-90a8-393dbccb0548"
	},
	{
		"id" : 4,
		"fecha_inicio" : "2020-01-01T10:00:00Z",
		"fecha_fin" : "2022-07-12T10:00:00Z",
		"nombreCampaña" : null,
		"objetivo" : null,
		"descripcion" : null,
		"lider" : null,
		"emailLider" : null,
		"telefonoLider" : null,
		"id_plantilla" : 4,
		"id_usuario" : "8a4b6394-0a7d-4ec6-90a8-393dbccb0548"
	},
	{
		"id" : 5,
		"fecha_inicio" : "2020-01-01T10:00:00Z",
		"fecha_fin" : "2022-07-12T10:00:00Z",
		"nombreCampaña" : null,
		"objetivo" : null,
		"descripcion" : null,
		"lider" : null,
		"emailLider" : null,
		"telefonoLider" : null,
		"id_plantilla" : 5,
		"id_usuario" : "8a4b6394-0a7d-4ec6-90a8-393dbccb0548"
	},
	{
		"id" : 6,
		"fecha_inicio" : "2020-01-01T10:00:00Z",
		"fecha_fin" : "2022-07-12T10:00:00Z",
		"nombreCampaña" : null,
		"objetivo" : null,
		"descripcion" : null,
		"lider" : null,
		"emailLider" : null,
		"telefonoLider" : null,
		"id_plantilla" : 3,
		"id_usuario" : "c4a4b0fe-cf3f-4037-b72f-c4d01436d89b"
	},
	{
		"id" : 7,
		"fecha_inicio" : "2020-01-01T10:00:00Z",
		"fecha_fin" : "2022-07-12T10:00:00Z",
		"nombreCampaña" : null,
		"objetivo" : null,
		"descripcion" : null,
		"lider" : null,
		"emailLider" : null,
		"telefonoLider" : null,
		"id_plantilla" : 4,
		"id_usuario" : "8b37a295-72d2-478f-99f6-b9d3831226a9"
	},
	{
		"id" : 8,
		"fecha_inicio" : "2020-01-01T10:00:00Z",
		"fecha_fin" : "2022-07-12T10:00:00Z",
		"nombreCampaña" : null,
		"objetivo" : null,
		"descripcion" : null,
		"lider" : null,
		"emailLider" : null,
		"telefonoLider" : null,
		"id_plantilla" : 5,
		"id_usuario" : "8b37a295-72d2-478f-99f6-b9d3831226a9"
	},
	{
		"id" : 9,
		"fecha_inicio" : "2020-01-01T10:00:00Z",
		"fecha_fin" : "2022-07-12T10:00:00Z",
		"nombreCampaña" : null,
		"objetivo" : null,
		"descripcion" : null,
		"lider" : null,
		"emailLider" : null,
		"telefonoLider" : null,
		"id_plantilla" : 1,
		"id_usuario" : "a1f4b1ba-9bca-4f9b-8f94-fbd991f968a4"
	},
	{
		"id" : 10,
		"fecha_inicio" : "2020-01-01T10:00:00Z",
		"fecha_fin" : "2022-07-12T10:00:00Z",
		"nombreCampaña" : null,
		"objetivo" : null,
		"descripcion" : null,
		"lider" : null,
		"emailLider" : null,
		"telefonoLider" : null,
		"id_plantilla" : 1,
		"id_usuario" : "3b407ee9-40d2-4be1-9757-31467a2c749b"
	},
	{
		"id" : 11,
		"fecha_inicio" : "2020-01-01T10:00:00Z",
		"fecha_fin" : "2022-07-12T10:00:00Z",
		"nombreCampaña" : null,
		"objetivo" : null,
		"descripcion" : null,
		"lider" : null,
		"emailLider" : null,
		"telefonoLider" : null,
		"id_plantilla" : 2,
		"id_usuario" : "3b407ee9-40d2-4be1-9757-31467a2c749b"
	},
	{
		"id" : 12,
		"fecha_inicio" : "2020-01-01T10:00:00Z",
		"fecha_fin" : "2022-07-12T10:00:00Z",
		"nombreCampaña" : null,
		"objetivo" : null,
		"descripcion" : null,
		"lider" : null,
		"emailLider" : null,
		"telefonoLider" : null,
		"id_plantilla" : 3,
		"id_usuario" : "3b407ee9-40d2-4be1-9757-31467a2c749b"
	},
	{
		"id" : 13,
		"fecha_inicio" : "2020-01-01T10:00:00Z",
		"fecha_fin" : "2022-07-12T10:00:00Z",
		"nombreCampaña" : null,
		"objetivo" : null,
		"descripcion" : null,
		"lider" : null,
		"emailLider" : null,
		"telefonoLider" : null,
		"id_plantilla" : 4,
		"id_usuario" : "3b407ee9-40d2-4be1-9757-31467a2c749b"
	},
	{
		"id" : 14,
		"fecha_inicio" : "2020-01-01T10:00:00Z",
		"fecha_fin" : "2022-07-12T10:00:00Z",
		"nombreCampaña" : null,
		"objetivo" : null,
		"descripcion" : null,
		"lider" : null,
		"emailLider" : null,
		"telefonoLider" : null,
		"id_plantilla" : 5,
		"id_usuario" : "3b407ee9-40d2-4be1-9757-31467a2c749b"
	},
	{
		"id" : 15,
		"fecha_inicio" : "2020-01-01T10:00:00Z",
		"fecha_fin" : "2022-07-12T10:00:00Z",
		"nombreCampaña" : null,
		"objetivo" : null,
		"descripcion" : null,
		"lider" : null,
		"emailLider" : null,
		"telefonoLider" : null,
		"id_plantilla" : 1,
		"id_usuario" : "f2bf5cb7-a860-4a20-8c71-f051f3d7b3c5"
	},
	{
		"id" : 16,
		"fecha_inicio" : "2020-01-01T10:00:00Z",
		"fecha_fin" : "2022-07-12T10:00:00Z",
		"nombreCampaña" : null,
		"objetivo" : null,
		"descripcion" : null,
		"lider" : null,
		"emailLider" : null,
		"telefonoLider" : null,
		"id_plantilla" : 2,
		"id_usuario" : "f2bf5cb7-a860-4a20-8c71-f051f3d7b3c5"
	},
	{
		"id" : 17,
		"fecha_inicio" : "2020-01-01T10:00:00Z",
		"fecha_fin" : "2022-07-12T10:00:00Z",
		"nombreCampaña" : null,
		"objetivo" : null,
		"descripcion" : null,
		"lider" : null,
		"emailLider" : null,
		"telefonoLider" : null,
		"id_plantilla" : 3,
		"id_usuario" : "f2bf5cb7-a860-4a20-8c71-f051f3d7b3c5"
	},
	{
		"id" : 18,
		"fecha_inicio" : "2020-01-01T10:00:00Z",
		"fecha_fin" : "2022-07-12T10:00:00Z",
		"nombreCampaña" : null,
		"objetivo" : null,
		"descripcion" : null,
		"lider" : null,
		"emailLider" : null,
		"telefonoLider" : null,
		"id_plantilla" : 4,
		"id_usuario" : "f2bf5cb7-a860-4a20-8c71-f051f3d7b3c5"
	},
	{
		"id" : 19,
		"fecha_inicio" : "2020-01-01T10:00:00Z",
		"fecha_fin" : "2022-07-12T10:00:00Z",
		"nombreCampaña" : null,
		"objetivo" : null,
		"descripcion" : null,
		"lider" : null,
		"emailLider" : null,
		"telefonoLider" : null,
		"id_plantilla" : 5,
		"id_usuario" : "f2bf5cb7-a860-4a20-8c71-f051f3d7b3c5"
	},
	{
		"id" : 20,
		"fecha_inicio" : "2020-01-01T10:00:00Z",
		"fecha_fin" : "2022-07-12T10:00:00Z",
		"nombreCampaña" : null,
		"objetivo" : null,
		"descripcion" : null,
		"lider" : null,
		"emailLider" : null,
		"telefonoLider" : null,
		"id_plantilla" : 1,
		"id_usuario" : "c84767b8-d6a1-4837-9c7a-89302fd42fd6"
	},
	{
		"id" : 21,
		"fecha_inicio" : "2020-01-01T10:00:00Z",
		"fecha_fin" : "2022-07-12T10:00:00Z",
		"nombreCampaña" : null,
		"objetivo" : null,
		"descripcion" : null,
		"lider" : null,
		"emailLider" : null,
		"telefonoLider" : null,
		"id_plantilla" : 2,
		"id_usuario" : "c84767b8-d6a1-4837-9c7a-89302fd42fd6"
	},
	{
		"id" : 22,
		"fecha_inicio" : "2020-01-01T10:00:00Z",
		"fecha_fin" : "2022-07-12T10:00:00Z",
		"nombreCampaña" : null,
		"objetivo" : null,
		"descripcion" : null,
		"lider" : null,
		"emailLider" : null,
		"telefonoLider" : null,
		"id_plantilla" : 3,
		"id_usuario" : "c84767b8-d6a1-4837-9c7a-89302fd42fd6"
	},
	{
		"id" : 23,
		"fecha_inicio" : "2020-01-01T10:00:00Z",
		"fecha_fin" : "2022-07-12T10:00:00Z",
		"nombreCampaña" : null,
		"objetivo" : null,
		"descripcion" : null,
		"lider" : null,
		"emailLider" : null,
		"telefonoLider" : null,
		"id_plantilla" : 4,
		"id_usuario" : "c84767b8-d6a1-4837-9c7a-89302fd42fd6"
	},
	{
		"id" : 24,
		"fecha_inicio" : "2020-01-01T10:00:00Z",
		"fecha_fin" : "2022-07-12T10:00:00Z",
		"nombreCampaña" : null,
		"objetivo" : null,
		"descripcion" : null,
		"lider" : null,
		"emailLider" : null,
		"telefonoLider" : null,
		"id_plantilla" : 5,
		"id_usuario" : "c84767b8-d6a1-4837-9c7a-89302fd42fd6"
	},
	{
		"id" : 25,
		"fecha_inicio" : "2020-01-01T10:00:00Z",
		"fecha_fin" : "2022-07-12T10:00:00Z",
		"nombreCampaña" : null,
		"objetivo" : null,
		"descripcion" : null,
		"lider" : null,
		"emailLider" : null,
		"telefonoLider" : null,
		"id_plantilla" : 1,
		"id_usuario" : "49d89d37-8b1a-40ed-a661-ca458b9d2ebb"
	},
	{
		"id" : 26,
		"fecha_inicio" : "2020-01-01T10:00:00Z",
		"fecha_fin" : "2022-07-12T10:00:00Z",
		"nombreCampaña" : null,
		"objetivo" : null,
		"descripcion" : null,
		"lider" : null,
		"emailLider" : null,
		"telefonoLider" : null,
		"id_plantilla" : 2,
		"id_usuario" : "49d89d37-8b1a-40ed-a661-ca458b9d2ebb"
	},
	{
		"id" : 27,
		"fecha_inicio" : "2020-01-01T10:00:00Z",
		"fecha_fin" : "2022-07-12T10:00:00Z",
		"nombreCampaña" : null,
		"objetivo" : null,
		"descripcion" : null,
		"lider" : null,
		"emailLider" : null,
		"telefonoLider" : null,
		"id_plantilla" : 3,
		"id_usuario" : "49d89d37-8b1a-40ed-a661-ca458b9d2ebb"
	},
	{
		"id" : 28,
		"fecha_inicio" : "2020-01-01T10:00:00Z",
		"fecha_fin" : "2022-07-12T10:00:00Z",
		"nombreCampaña" : null,
		"objetivo" : null,
		"descripcion" : null,
		"lider" : null,
		"emailLider" : null,
		"telefonoLider" : null,
		"id_plantilla" : 4,
		"id_usuario" : "49d89d37-8b1a-40ed-a661-ca458b9d2ebb"
	},
	{
		"id" : 29,
		"fecha_inicio" : "2020-01-01T10:00:00Z",
		"fecha_fin" : "2022-07-12T10:00:00Z",
		"nombreCampaña" : null,
		"objetivo" : null,
		"descripcion" : null,
		"lider" : null,
		"emailLider" : null,
		"telefonoLider" : null,
		"id_plantilla" : 5,
		"id_usuario" : "49d89d37-8b1a-40ed-a661-ca458b9d2ebb"
	},
	{
		"id" : 30,
		"fecha_inicio" : "2020-01-01T10:00:00Z",
		"fecha_fin" : "2022-07-12T10:00:00Z",
		"nombreCampaña" : null,
		"objetivo" : null,
		"descripcion" : null,
		"lider" : null,
		"emailLider" : null,
		"telefonoLider" : null,
		"id_plantilla" : 1,
		"id_usuario" : "65016c0d-4f35-4ebd-9319-8c9f2b062777"
	},
	{
		"id" : 31,
		"fecha_inicio" : "2020-01-01T10:00:00Z",
		"fecha_fin" : "2022-07-12T10:00:00Z",
		"nombreCampaña" : null,
		"objetivo" : null,
		"descripcion" : null,
		"lider" : null,
		"emailLider" : null,
		"telefonoLider" : null,
		"id_plantilla" : 2,
		"id_usuario" : "65016c0d-4f35-4ebd-9319-8c9f2b062777"
	},
	{
		"id" : 32,
		"fecha_inicio" : "2020-01-01T10:00:00Z",
		"fecha_fin" : "2022-07-12T10:00:00Z",
		"nombreCampaña" : null,
		"objetivo" : null,
		"descripcion" : null,
		"lider" : null,
		"emailLider" : null,
		"telefonoLider" : null,
		"id_plantilla" : 3,
		"id_usuario" : "65016c0d-4f35-4ebd-9319-8c9f2b062777"
	},
	{
		"id" : 33,
		"fecha_inicio" : "2020-01-01T10:00:00Z",
		"fecha_fin" : "2022-07-12T10:00:00Z",
		"nombreCampaña" : null,
		"objetivo" : null,
		"descripcion" : null,
		"lider" : null,
		"emailLider" : null,
		"telefonoLider" : null,
		"id_plantilla" : 4,
		"id_usuario" : "65016c0d-4f35-4ebd-9319-8c9f2b062777"
	},
	{
		"id" : 34,
		"fecha_inicio" : "2020-01-01T10:00:00Z",
		"fecha_fin" : "2022-07-12T10:00:00Z",
		"nombreCampaña" : null,
		"objetivo" : null,
		"descripcion" : null,
		"lider" : null,
		"emailLider" : null,
		"telefonoLider" : null,
		"id_plantilla" : 5,
		"id_usuario" : "65016c0d-4f35-4ebd-9319-8c9f2b062777"
	},
	{
		"id" : 35,
		"fecha_inicio" : "2020-01-01T10:00:00Z",
		"fecha_fin" : "2022-07-12T10:00:00Z",
		"nombreCampaña" : null,
		"objetivo" : null,
		"descripcion" : null,
		"lider" : null,
		"emailLider" : null,
		"telefonoLider" : null,
		"id_plantilla" : 1,
		"id_usuario" : "7e885630-6f97-49d1-8246-1467d2a87e35"
	},
	{
		"id" : 36,
		"fecha_inicio" : "2020-01-01T10:00:00Z",
		"fecha_fin" : "2022-07-12T10:00:00Z",
		"nombreCampaña" : null,
		"objetivo" : null,
		"descripcion" : null,
		"lider" : null,
		"emailLider" : null,
		"telefonoLider" : null,
		"id_plantilla" : 2,
		"id_usuario" : "7e885630-6f97-49d1-8246-1467d2a87e35"
	},
	{
		"id" : 37,
		"fecha_inicio" : "2020-01-01T10:00:00Z",
		"fecha_fin" : "2022-07-12T10:00:00Z",
		"nombreCampaña" : null,
		"objetivo" : null,
		"descripcion" : null,
		"lider" : null,
		"emailLider" : null,
		"telefonoLider" : null,
		"id_plantilla" : 3,
		"id_usuario" : "7e885630-6f97-49d1-8246-1467d2a87e35"
	},
	{
		"id" : 38,
		"fecha_inicio" : "2020-01-01T10:00:00Z",
		"fecha_fin" : "2022-07-12T10:00:00Z",
		"nombreCampaña" : null,
		"objetivo" : null,
		"descripcion" : null,
		"lider" : null,
		"emailLider" : null,
		"telefonoLider" : null,
		"id_plantilla" : 4,
		"id_usuario" : "7e885630-6f97-49d1-8246-1467d2a87e35"
	},
	{
		"id" : 39,
		"fecha_inicio" : "2020-01-01T10:00:00Z",
		"fecha_fin" : "2022-07-12T10:00:00Z",
		"nombreCampaña" : null,
		"objetivo" : null,
		"descripcion" : null,
		"lider" : null,
		"emailLider" : null,
		"telefonoLider" : null,
		"id_plantilla" : 5,
		"id_usuario" : "7e885630-6f97-49d1-8246-1467d2a87e35"
	},
	{
		"id" : 40,
		"fecha_inicio" : "2020-01-01T10:00:00Z",
		"fecha_fin" : "2022-07-12T10:00:00Z",
		"nombreCampaña" : null,
		"objetivo" : null,
		"descripcion" : null,
		"lider" : null,
		"emailLider" : null,
		"telefonoLider" : null,
		"id_plantilla" : 1,
		"id_usuario" : "9043f7b0-1876-4eef-937d-5357cf610a60"
	},
	{
		"id" : 41,
		"fecha_inicio" : "2020-01-01T10:00:00Z",
		"fecha_fin" : "2022-07-12T10:00:00Z",
		"nombreCampaña" : null,
		"objetivo" : null,
		"descripcion" : null,
		"lider" : null,
		"emailLider" : null,
		"telefonoLider" : null,
		"id_plantilla" : 2,
		"id_usuario" : "9043f7b0-1876-4eef-937d-5357cf610a60"
	},
	{
		"id" : 42,
		"fecha_inicio" : "2020-01-01T10:00:00Z",
		"fecha_fin" : "2022-07-12T10:00:00Z",
		"nombreCampaña" : null,
		"objetivo" : null,
		"descripcion" : null,
		"lider" : null,
		"emailLider" : null,
		"telefonoLider" : null,
		"id_plantilla" : 3,
		"id_usuario" : "9043f7b0-1876-4eef-937d-5357cf610a60"
	},
	{
		"id" : 43,
		"fecha_inicio" : "2020-01-01T10:00:00Z",
		"fecha_fin" : "2022-07-12T10:00:00Z",
		"nombreCampaña" : null,
		"objetivo" : null,
		"descripcion" : null,
		"lider" : null,
		"emailLider" : null,
		"telefonoLider" : null,
		"id_plantilla" : 4,
		"id_usuario" : "9043f7b0-1876-4eef-937d-5357cf610a60"
	},
	{
		"id" : 44,
		"fecha_inicio" : "2020-01-01T10:00:00Z",
		"fecha_fin" : "2022-07-12T10:00:00Z",
		"nombreCampaña" : null,
		"objetivo" : null,
		"descripcion" : null,
		"lider" : null,
		"emailLider" : null,
		"telefonoLider" : null,
		"id_plantilla" : 5,
		"id_usuario" : "9043f7b0-1876-4eef-937d-5357cf610a60"
	},
	{
		"id" : 45,
		"fecha_inicio" : "2020-01-01T10:00:00Z",
		"fecha_fin" : "2022-07-12T10:00:00Z",
		"nombreCampaña" : null,
		"objetivo" : null,
		"descripcion" : null,
		"lider" : null,
		"emailLider" : null,
		"telefonoLider" : null,
		"id_plantilla" : 1,
		"id_usuario" : "21b109a6-6eb1-42d1-a8ba-36f403158cd5"
	},
	{
		"id" : 46,
		"fecha_inicio" : "2020-01-01T10:00:00Z",
		"fecha_fin" : "2022-07-12T10:00:00Z",
		"nombreCampaña" : null,
		"objetivo" : null,
		"descripcion" : null,
		"lider" : null,
		"emailLider" : null,
		"telefonoLider" : null,
		"id_plantilla" : 2,
		"id_usuario" : "21b109a6-6eb1-42d1-a8ba-36f403158cd5"
	},
	{
		"id" : 47,
		"fecha_inicio" : "2020-01-01T10:00:00Z",
		"fecha_fin" : "2022-07-12T10:00:00Z",
		"nombreCampaña" : null,
		"objetivo" : null,
		"descripcion" : null,
		"lider" : null,
		"emailLider" : null,
		"telefonoLider" : null,
		"id_plantilla" : 3,
		"id_usuario" : "21b109a6-6eb1-42d1-a8ba-36f403158cd5"
	},
	{
		"id" : 48,
		"fecha_inicio" : "2020-01-01T10:00:00Z",
		"fecha_fin" : "2022-07-12T10:00:00Z",
		"nombreCampaña" : null,
		"objetivo" : null,
		"descripcion" : null,
		"lider" : null,
		"emailLider" : null,
		"telefonoLider" : null,
		"id_plantilla" : 4,
		"id_usuario" : "21b109a6-6eb1-42d1-a8ba-36f403158cd5"
	},
	{
		"id" : 49,
		"fecha_inicio" : "2020-01-01T10:00:00Z",
		"fecha_fin" : "2022-07-12T10:00:00Z",
		"nombreCampaña" : null,
		"objetivo" : null,
		"descripcion" : null,
		"lider" : null,
		"emailLider" : null,
		"telefonoLider" : null,
		"id_plantilla" : 5,
		"id_usuario" : "21b109a6-6eb1-42d1-a8ba-36f403158cd5"
	},
	{
		"id" : 50,
		"fecha_inicio" : "2020-01-01T10:00:00Z",
		"fecha_fin" : "2022-07-12T10:00:00Z",
		"nombreCampaña" : null,
		"objetivo" : null,
		"descripcion" : null,
		"lider" : null,
		"emailLider" : null,
		"telefonoLider" : null,
		"id_plantilla" : 1,
		"id_usuario" : "a1fa5151-6574-45a7-a164-667b1a1625fa"
	},
	{
		"id" : 51,
		"fecha_inicio" : "2020-01-01T10:00:00Z",
		"fecha_fin" : "2022-07-12T10:00:00Z",
		"nombreCampaña" : null,
		"objetivo" : null,
		"descripcion" : null,
		"lider" : null,
		"emailLider" : null,
		"telefonoLider" : null,
		"id_plantilla" : 2,
		"id_usuario" : "a1fa5151-6574-45a7-a164-667b1a1625fa"
	},
	{
		"id" : 52,
		"fecha_inicio" : "2020-01-01T10:00:00Z",
		"fecha_fin" : "2022-07-12T10:00:00Z",
		"nombreCampaña" : null,
		"objetivo" : null,
		"descripcion" : null,
		"lider" : null,
		"emailLider" : null,
		"telefonoLider" : null,
		"id_plantilla" : 3,
		"id_usuario" : "a1fa5151-6574-45a7-a164-667b1a1625fa"
	},
	{
		"id" : 53,
		"fecha_inicio" : "2020-01-01T10:00:00Z",
		"fecha_fin" : "2022-07-12T10:00:00Z",
		"nombreCampaña" : null,
		"objetivo" : null,
		"descripcion" : null,
		"lider" : null,
		"emailLider" : null,
		"telefonoLider" : null,
		"id_plantilla" : 4,
		"id_usuario" : "a1fa5151-6574-45a7-a164-667b1a1625fa"
	},
	{
		"id" : 54,
		"fecha_inicio" : "2020-01-01T10:00:00Z",
		"fecha_fin" : "2022-07-12T10:00:00Z",
		"nombreCampaña" : null,
		"objetivo" : null,
		"descripcion" : null,
		"lider" : null,
		"emailLider" : null,
		"telefonoLider" : null,
		"id_plantilla" : 5,
		"id_usuario" : "a1fa5151-6574-45a7-a164-667b1a1625fa"
	},
	{
		"id" : 55,
		"fecha_inicio" : "2020-01-01T10:00:00Z",
		"fecha_fin" : "2022-07-12T10:00:00Z",
		"nombreCampaña" : null,
		"objetivo" : null,
		"descripcion" : null,
		"lider" : null,
		"emailLider" : null,
		"telefonoLider" : null,
		"id_plantilla" : 1,
		"id_usuario" : "f8248cb5-ee15-4b55-8070-58e5afb635c9"
	},
	{
		"id" : 56,
		"fecha_inicio" : "2020-01-01T10:00:00Z",
		"fecha_fin" : "2022-07-12T10:00:00Z",
		"nombreCampaña" : null,
		"objetivo" : null,
		"descripcion" : null,
		"lider" : null,
		"emailLider" : null,
		"telefonoLider" : null,
		"id_plantilla" : 2,
		"id_usuario" : "f8248cb5-ee15-4b55-8070-58e5afb635c9"
	},
	{
		"id" : 57,
		"fecha_inicio" : "2020-01-01T10:00:00Z",
		"fecha_fin" : "2022-07-12T10:00:00Z",
		"nombreCampaña" : null,
		"objetivo" : null,
		"descripcion" : null,
		"lider" : null,
		"emailLider" : null,
		"telefonoLider" : null,
		"id_plantilla" : 1,
		"id_usuario" : "3c5e68b4-212f-4cfe-b0c4-cb37fd4dff12"
	},
	{
		"id" : 58,
		"fecha_inicio" : "2020-01-01T10:00:00Z",
		"fecha_fin" : "2022-07-12T10:00:00Z",
		"nombreCampaña" : null,
		"objetivo" : null,
		"descripcion" : null,
		"lider" : null,
		"emailLider" : null,
		"telefonoLider" : null,
		"id_plantilla" : 2,
		"id_usuario" : "3c5e68b4-212f-4cfe-b0c4-cb37fd4dff12"
	},
	{
		"id" : 59,
		"fecha_inicio" : "2020-01-01T10:00:00Z",
		"fecha_fin" : "2022-07-12T10:00:00Z",
		"nombreCampaña" : null,
		"objetivo" : null,
		"descripcion" : null,
		"lider" : null,
		"emailLider" : null,
		"telefonoLider" : null,
		"id_plantilla" : 3,
		"id_usuario" : "3c5e68b4-212f-4cfe-b0c4-cb37fd4dff12"
	},
	{
		"id" : 60,
		"fecha_inicio" : "2020-01-01T10:00:00Z",
		"fecha_fin" : "2022-07-12T10:00:00Z",
		"nombreCampaña" : null,
		"objetivo" : null,
		"descripcion" : null,
		"lider" : null,
		"emailLider" : null,
		"telefonoLider" : null,
		"id_plantilla" : 4,
		"id_usuario" : "3c5e68b4-212f-4cfe-b0c4-cb37fd4dff12"
	},
	{
		"id" : 61,
		"fecha_inicio" : "2020-01-01T10:00:00Z",
		"fecha_fin" : "2022-07-12T10:00:00Z",
		"nombreCampaña" : null,
		"objetivo" : null,
		"descripcion" : null,
		"lider" : null,
		"emailLider" : null,
		"telefonoLider" : null,
		"id_plantilla" : 5,
		"id_usuario" : "3c5e68b4-212f-4cfe-b0c4-cb37fd4dff12"
	},
	{
		"id" : 62,
		"fecha_inicio" : "2020-01-01T10:00:00Z",
		"fecha_fin" : "2022-07-12T10:00:00Z",
		"nombreCampaña" : null,
		"objetivo" : null,
		"descripcion" : null,
		"lider" : null,
		"emailLider" : null,
		"telefonoLider" : null,
		"id_plantilla" : 1,
		"id_usuario" : "a2a9e80f-01f4-465a-814c-d8a5ae51c168"
	},
	{
		"id" : 63,
		"fecha_inicio" : "2020-01-01T10:00:00Z",
		"fecha_fin" : "2022-07-12T10:00:00Z",
		"nombreCampaña" : null,
		"objetivo" : null,
		"descripcion" : null,
		"lider" : null,
		"emailLider" : null,
		"telefonoLider" : null,
		"id_plantilla" : 2,
		"id_usuario" : "a2a9e80f-01f4-465a-814c-d8a5ae51c168"
	},
	{
		"id" : 64,
		"fecha_inicio" : "2020-01-01T10:00:00Z",
		"fecha_fin" : "2022-07-12T10:00:00Z",
		"nombreCampaña" : null,
		"objetivo" : null,
		"descripcion" : null,
		"lider" : null,
		"emailLider" : null,
		"telefonoLider" : null,
		"id_plantilla" : 3,
		"id_usuario" : "a2a9e80f-01f4-465a-814c-d8a5ae51c168"
	},
	{
		"id" : 65,
		"fecha_inicio" : "2020-01-01T10:00:00Z",
		"fecha_fin" : "2022-07-12T10:00:00Z",
		"nombreCampaña" : null,
		"objetivo" : null,
		"descripcion" : null,
		"lider" : null,
		"emailLider" : null,
		"telefonoLider" : null,
		"id_plantilla" : 4,
		"id_usuario" : "a2a9e80f-01f4-465a-814c-d8a5ae51c168"
	},
	{
		"id" : 66,
		"fecha_inicio" : "2020-01-01T10:00:00Z",
		"fecha_fin" : "2022-07-12T10:00:00Z",
		"nombreCampaña" : null,
		"objetivo" : null,
		"descripcion" : null,
		"lider" : null,
		"emailLider" : null,
		"telefonoLider" : null,
		"id_plantilla" : 5,
		"id_usuario" : "a2a9e80f-01f4-465a-814c-d8a5ae51c168"
	},
	{
		"id" : 67,
		"fecha_inicio" : "2020-01-01T10:00:00Z",
		"fecha_fin" : "2022-07-12T10:00:00Z",
		"nombreCampaña" : null,
		"objetivo" : null,
		"descripcion" : null,
		"lider" : null,
		"emailLider" : null,
		"telefonoLider" : null,
		"id_plantilla" : 2,
		"id_usuario" : "a1f4b1ba-9bca-4f9b-8f94-fbd991f968a4"
	},
	{
		"id" : 68,
		"fecha_inicio" : "2020-01-01T10:00:00Z",
		"fecha_fin" : "2022-07-12T10:00:00Z",
		"nombreCampaña" : null,
		"objetivo" : null,
		"descripcion" : null,
		"lider" : null,
		"emailLider" : null,
		"telefonoLider" : null,
		"id_plantilla" : 3,
		"id_usuario" : "78ebff69-0bbd-489c-8244-57d94234453c"
	},
	{
		"id" : 69,
		"fecha_inicio" : "2020-01-01T10:00:00Z",
		"fecha_fin" : "2022-07-12T10:00:00Z",
		"nombreCampaña" : null,
		"objetivo" : null,
		"descripcion" : null,
		"lider" : null,
		"emailLider" : null,
		"telefonoLider" : null,
		"id_plantilla" : 3,
		"id_usuario" : "f23722e9-5d25-43c4-a296-5cbde6a950ea"
	},
	{
		"id" : 89,
		"fecha_inicio" : "2020-01-01T10:00:00Z",
		"fecha_fin" : "2022-07-12T10:00:00Z",
		"nombreCampaña" : null,
		"objetivo" : null,
		"descripcion" : null,
		"lider" : null,
		"emailLider" : null,
		"telefonoLider" : null,
		"id_plantilla" : 4,
		"id_usuario" : "15c84d2e-ffaa-42fa-b6f1-f6564b74af03"
	},
	{
		"id" : 90,
		"fecha_inicio" : "2020-01-01T10:00:00Z",
		"fecha_fin" : "2022-07-12T10:00:00Z",
		"nombreCampaña" : null,
		"objetivo" : null,
		"descripcion" : null,
		"lider" : null,
		"emailLider" : null,
		"telefonoLider" : null,
		"id_plantilla" : 4,
		"id_usuario" : "1bc7f634-3c4b-409f-9296-83410c87d9b4"
	},
	{
		"id" : 91,
		"fecha_inicio" : "2020-01-01T10:00:00Z",
		"fecha_fin" : "2022-07-12T10:00:00Z",
		"nombreCampaña" : null,
		"objetivo" : null,
		"descripcion" : null,
		"lider" : null,
		"emailLider" : null,
		"telefonoLider" : null,
		"id_plantilla" : 4,
		"id_usuario" : "b0fc9604-43e9-40f8-9b28-de57d3a6e612"
	},
	{
		"id" : 92,
		"fecha_inicio" : "2020-01-01T10:00:00Z",
		"fecha_fin" : "2022-07-12T10:00:00Z",
		"nombreCampaña" : null,
		"objetivo" : null,
		"descripcion" : null,
		"lider" : null,
		"emailLider" : null,
		"telefonoLider" : null,
		"id_plantilla" : 5,
		"id_usuario" : "15c84d2e-ffaa-42fa-b6f1-f6564b74af03"
	},
	{
		"id" : 93,
		"fecha_inicio" : "2020-01-01T10:00:00Z",
		"fecha_fin" : "2022-07-12T10:00:00Z",
		"nombreCampaña" : null,
		"objetivo" : null,
		"descripcion" : null,
		"lider" : null,
		"emailLider" : null,
		"telefonoLider" : null,
		"id_plantilla" : 5,
		"id_usuario" : "1bc7f634-3c4b-409f-9296-83410c87d9b4"
	},
	{
		"id" : 94,
		"fecha_inicio" : "2020-01-01T10:00:00Z",
		"fecha_fin" : "2022-07-12T10:00:00Z",
		"nombreCampaña" : null,
		"objetivo" : null,
		"descripcion" : null,
		"lider" : null,
		"emailLider" : null,
		"telefonoLider" : null,
		"id_plantilla" : 5,
		"id_usuario" : "b0fc9604-43e9-40f8-9b28-de57d3a6e612"
	}
]}
